[
    {
        "video_id": "9Xeepzg1B8I",
        "title": "Which Celebrity Punches The Hardest?",
        "publishedAt": "2025-09-19T16:00:03Z",
        "duration": "PT47S",
        "viewCount": "165794092",
        "likeCount": "3361694",
        "commentCount": "10063"
    },
    {
        "video_id": "TNtpUQbW4mg",
        "title": "This Is How The Pyramids Were Built",
        "publishedAt": "2025-03-18T16:00:00Z",
        "duration": "PT13S",
        "viewCount": "385597893",
        "likeCount": "8749682",
        "commentCount": "24098"
    },
    {
        "video_id": "T8I165Qxeo8",
        "title": "Sprinting with More and More Money",
        "publishedAt": "2024-05-30T16:00:01Z",
        "duration": "PT29S",
        "viewCount": "321836406",
        "likeCount": "11967680",
        "commentCount": "86379"
    },
    {
        "video_id": "KrLj6nc516A",
        "title": "$1 vs $100,000,000 Car!",
        "publishedAt": "2023-09-16T16:00:01Z",
        "duration": "PT16M28S",
        "viewCount": "538804155",
        "likeCount": "8043360",
        "commentCount": "156779"
    },
    {
        "video_id": "x9TQ6culXIA",
        "title": "World's Biggest YouTubers Fight for $1,000,000",
        "publishedAt": "2021-12-16T21:00:00Z",
        "duration": "PT12M5S",
        "viewCount": "105842280",
        "likeCount": "3133858",
        "commentCount": "83531"
    },
    {
        "video_id": "5Hg_QSIJm8I",
        "title": "I Gave $200,000 To People Who Lost Their Jobs (Corona Virus)",
        "publishedAt": "2020-05-07T19:59:59Z",
        "duration": "PT15M19S",
        "viewCount": "47366079",
        "likeCount": "1401976",
        "commentCount": "63342"
    },
    {
        "video_id": "AA-VpIj8F5Y",
        "title": "Last To Stop Running Wins $20,000",
        "publishedAt": "2019-06-06T20:00:00Z",
        "duration": "PT14M58S",
        "viewCount": "124197387",
        "likeCount": "2388889",
        "commentCount": "65757"
    },
    {
        "video_id": "Gz3yak1cl-8",
        "title": "Last To Leave Circle Wins $10,000 - Challenge",
        "publishedAt": "2018-10-12T22:05:04Z",
        "duration": "PT16M36S",
        "viewCount": "98811202",
        "likeCount": "1675406",
        "commentCount": "59029"
    },
    {
        "video_id": "szt8xabJoSo",
        "title": "Donating $10,000 To Fortnite Streamers If They Win",
        "publishedAt": "2018-03-03T23:21:02Z",
        "duration": "PT14M31S",
        "viewCount": "11388780",
        "likeCount": "273463",
        "commentCount": "15632"
    },
    {
        "video_id": "KzwTYZ2W3ZA",
        "title": "Microwaving A Microwave",
        "publishedAt": "2016-12-09T02:45:18Z",
        "duration": "PT9M5S",
        "viewCount": "11876322",
        "likeCount": "439260",
        "commentCount": "41196"
    },
    {
        "video_id": "zjC48c3ptt0",
        "title": "Scheduled Uploaded 6 Months Ago (REACTION)",
        "publishedAt": "2016-04-06T21:02:02Z",
        "duration": "PT5M22S",
        "viewCount": "150184",
        "likeCount": "5295",
        "commentCount": "480"
    },
    {
        "video_id": "hD_Af6W2qug",
        "title": "Dear Razer Can I Have My 70$ Back?????",
        "publishedAt": "2015-11-29T21:10:16Z",
        "duration": "PT2M59S",
        "viewCount": "7616850",
        "likeCount": "348178",
        "commentCount": "24390"
    },
    {
        "video_id": "GxTVDClFXuc",
        "title": "MrBeast6000Subs",
        "publishedAt": "2015-08-23T11:00:00Z",
        "duration": "PT5M20S",
        "viewCount": "949200",
        "likeCount": "58614",
        "commentCount": "5215"
    },
    {
        "video_id": "zpCwHwWgbsI",
        "title": "What Is Spam404?????",
        "publishedAt": "2015-07-15T15:05:18Z",
        "duration": "PT5M11S",
        "viewCount": "63006",
        "likeCount": "1489",
        "commentCount": "360"
    },
    {
        "video_id": "56OkH6ocYZU",
        "title": "L0114R - Biblical Creeper Post for Post @L0114R",
        "publishedAt": "2015-05-15T16:48:54Z",
        "duration": "PT1M28S",
        "viewCount": "63093",
        "likeCount": "1284",
        "commentCount": "249"
    },
    {
        "video_id": "6BNOWeYFyP8",
        "title": "MageCraft - Beginners tutorial. (The app)",
        "publishedAt": "2014-11-17T02:25:46Z",
        "duration": "PT8M47S",
        "viewCount": "63541",
        "likeCount": "1397",
        "commentCount": "226"
    },
    {
        "video_id": "S9PIukDRcvk",
        "title": "Update",
        "publishedAt": "2014-03-13T00:19:29Z",
        "duration": "PT4M21S",
        "viewCount": "76995",
        "likeCount": "2031",
        "commentCount": "362"
    },
    {
        "video_id": "mVkT6Cd9SoI",
        "title": "Camping Montage.... LOL",
        "publishedAt": "2013-08-05T21:12:41Z",
        "duration": "PT3M20S",
        "viewCount": "114120",
        "likeCount": "3707",
        "commentCount": "541"
    },
    {
        "video_id": "2XVcLrB7B3Y",
        "title": "Worst Minecraft Saw Trap Ever???",
        "publishedAt": "2012-02-20T22:42:32Z",
        "duration": "PT2M37S",
        "viewCount": "33727733",
        "likeCount": "1389921",
        "commentCount": "150228"
    }
]